[
    {
        "asOfDate": "2023-09-30 00:00:00",
        "periodType": "3M",
        "currencyCode": "USD",
        "AmortizationCashFlow": 129000000.0,
        "AmortizationOfIntangibles": 129000000.0,
        "BeginningCashPosition": NaN,
        "CapitalExpenditure": NaN,
        "CashDividendsPaid": NaN,
        "CashFlowFromContinuingFinancingActivities": NaN,
        "CashFlowFromContinuingInvestingActivities": NaN,
        "CashFlowFromContinuingOperatingActivities": NaN,
        "ChangeInAccountPayable": NaN,
        "ChangeInAccruedExpense": NaN,
        "ChangeInCashSupplementalAsReported": NaN,
        "ChangeInOtherCurrentAssets": NaN,
        "ChangeInOtherWorkingCapital": NaN,
        "ChangeInPayable": NaN,
        "ChangeInPayablesAndAccruedExpense": NaN,
        "ChangeInReceivables": NaN,
        "ChangeInWorkingCapital": NaN,
        "ChangesInAccountReceivables": NaN,
        "ChangesInCash": NaN,
        "CommonStockDividendPaid": NaN,
        "CommonStockPayments": NaN,
        "DeferredIncomeTax": NaN,
        "DeferredTax": NaN,
        "Depreciation": NaN,
        "DepreciationAmortizationDepletion": NaN,
        "DepreciationAndAmortization": NaN,
        "EffectOfExchangeRateChanges": NaN,
        "EndCashPosition": NaN,
        "FinancingCashFlow": NaN,
        "FreeCashFlow": NaN,
        "GainLossOnInvestmentSecurities": NaN,
        "InvestingCashFlow": NaN,
        "IssuanceOfDebt": NaN,
        "LongTermDebtIssuance": NaN,
        "LongTermDebtPayments": NaN,
        "NetBusinessPurchaseAndSale": NaN,
        "NetCommonStockIssuance": NaN,
        "NetIncome": NaN,
        "NetIncomeFromContinuingOperations": NaN,
        "NetInvestmentPurchaseAndSale": NaN,
        "NetIssuancePaymentsOfDebt": NaN,
        "NetLongTermDebtIssuance": NaN,
        "NetOtherFinancingCharges": NaN,
        "NetOtherInvestingChanges": NaN,
        "NetPPEPurchaseAndSale": NaN,
        "OperatingCashFlow": NaN,
        "OperatingGainsLosses": NaN,
        "OtherNonCashItems": NaN,
        "ProceedsFromStockOptionExercised": NaN,
        "PurchaseOfBusiness": NaN,
        "PurchaseOfInvestment": NaN,
        "PurchaseOfPPE": NaN,
        "RepaymentOfDebt": NaN,
        "RepurchaseOfCapitalStock": NaN,
        "SaleOfInvestment": NaN,
        "StockBasedCompensation": NaN
    },
    {
        "asOfDate": "2024-03-31 00:00:00",
        "periodType": "3M",
        "currencyCode": "USD",
        "AmortizationCashFlow": NaN,
        "AmortizationOfIntangibles": NaN,
        "BeginningCashPosition": 24048000000.0,
        "CapitalExpenditure": -12012000000.0,
        "CashDividendsPaid": 0.0,
        "CashFlowFromContinuingFinancingActivities": -19714000000.0,
        "CashFlowFromContinuingInvestingActivities": -8564000000.0,
        "CashFlowFromContinuingOperatingActivities": 28848000000.0,
        "ChangeInAccountPayable": -2124000000.0,
        "ChangeInAccruedExpense": -5376000000.0,
        "ChangeInCashSupplementalAsReported": 445000000.0,
        "ChangeInOtherCurrentAssets": -1000000000.0,
        "ChangeInOtherWorkingCapital": 2870000000.0,
        "ChangeInPayable": -2124000000.0,
        "ChangeInPayablesAndAccruedExpense": -7500000000.0,
        "ChangeInReceivables": 3167000000.0,
        "ChangeInWorkingCapital": -2463000000.0,
        "ChangesInAccountReceivables": 3167000000.0,
        "ChangesInCash": 570000000.0,
        "CommonStockDividendPaid": 0.0,
        "CommonStockPayments": -15696000000.0,
        "DeferredIncomeTax": 419000000.0,
        "DeferredTax": 419000000.0,
        "Depreciation": 3413000000.0,
        "DepreciationAmortizationDepletion": 3413000000.0,
        "DepreciationAndAmortization": 3413000000.0,
        "EffectOfExchangeRateChanges": -125000000.0,
        "EndCashPosition": 24493000000.0,
        "FinancingCashFlow": -19714000000.0,
        "FreeCashFlow": 16836000000.0,
        "GainLossOnInvestmentSecurities": -1781000000.0,
        "InvestingCashFlow": -8564000000.0,
        "IssuanceOfDebt": 1982000000.0,
        "LongTermDebtIssuance": 1982000000.0,
        "LongTermDebtPayments": -3079000000.0,
        "NetBusinessPurchaseAndSale": -61000000.0,
        "NetCommonStockIssuance": -15696000000.0,
        "NetIncome": 23662000000.0,
        "NetIncomeFromContinuingOperations": 23662000000.0,
        "NetInvestmentPurchaseAndSale": 3408000000.0,
        "NetIssuancePaymentsOfDebt": -1097000000.0,
        "NetLongTermDebtIssuance": -1097000000.0,
        "NetOtherFinancingCharges": 8000000.0,
        "NetOtherInvestingChanges": 101000000.0,
        "NetPPEPurchaseAndSale": -12012000000.0,
        "OperatingCashFlow": 28848000000.0,
        "OperatingGainsLosses": -1781000000.0,
        "OtherNonCashItems": 334000000.0,
        "ProceedsFromStockOptionExercised": -2929000000.0,
        "PurchaseOfBusiness": -61000000.0,
        "PurchaseOfInvestment": -21890000000.0,
        "PurchaseOfPPE": -12012000000.0,
        "RepaymentOfDebt": -3079000000.0,
        "RepurchaseOfCapitalStock": -15696000000.0,
        "SaleOfInvestment": 25298000000.0,
        "StockBasedCompensation": 5264000000.0
    },
    {
        "asOfDate": "2024-06-30 00:00:00",
        "periodType": "3M",
        "currencyCode": "USD",
        "AmortizationCashFlow": NaN,
        "AmortizationOfIntangibles": NaN,
        "BeginningCashPosition": 24493000000.0,
        "CapitalExpenditure": -13186000000.0,
        "CashDividendsPaid": -2466000000.0,
        "CashFlowFromContinuingFinancingActivities": -20889000000.0,
        "CashFlowFromContinuingInvestingActivities": -2781000000.0,
        "CashFlowFromContinuingOperatingActivities": 26640000000.0,
        "ChangeInAccountPayable": 1561000000.0,
        "ChangeInAccruedExpense": 297000000.0,
        "ChangeInCashSupplementalAsReported": 2732000000.0,
        "ChangeInOtherCurrentAssets": -532000000.0,
        "ChangeInOtherWorkingCapital": -3539000000.0,
        "ChangeInPayable": 1561000000.0,
        "ChangeInPayablesAndAccruedExpense": 1858000000.0,
        "ChangeInReceivables": -3057000000.0,
        "ChangeInWorkingCapital": -5270000000.0,
        "ChangesInAccountReceivables": -3057000000.0,
        "ChangesInCash": 2970000000.0,
        "CommonStockDividendPaid": -2466000000.0,
        "CommonStockPayments": -15684000000.0,
        "DeferredIncomeTax": -3157000000.0,
        "DeferredTax": -3157000000.0,
        "Depreciation": 3708000000.0,
        "DepreciationAmortizationDepletion": 3708000000.0,
        "DepreciationAndAmortization": 3708000000.0,
        "EffectOfExchangeRateChanges": -238000000.0,
        "EndCashPosition": 27225000000.0,
        "FinancingCashFlow": -20889000000.0,
        "FreeCashFlow": 13454000000.0,
        "GainLossOnInvestmentSecurities": 1024000000.0,
        "InvestingCashFlow": -2781000000.0,
        "IssuanceOfDebt": 2893000000.0,
        "LongTermDebtIssuance": 2893000000.0,
        "LongTermDebtPayments": -2423000000.0,
        "NetBusinessPurchaseAndSale": -26000000.0,
        "NetCommonStockIssuance": -15684000000.0,
        "NetIncome": 23619000000.0,
        "NetIncomeFromContinuingOperations": 23619000000.0,
        "NetInvestmentPurchaseAndSale": 10564000000.0,
        "NetIssuancePaymentsOfDebt": 470000000.0,
        "NetLongTermDebtIssuance": 470000000.0,
        "NetOtherFinancingCharges": 0.0,
        "NetOtherInvestingChanges": -133000000.0,
        "NetPPEPurchaseAndSale": -13186000000.0,
        "OperatingCashFlow": 26640000000.0,
        "OperatingGainsLosses": 1024000000.0,
        "OtherNonCashItems": 851000000.0,
        "ProceedsFromStockOptionExercised": -3209000000.0,
        "PurchaseOfBusiness": -26000000.0,
        "PurchaseOfInvestment": -23320000000.0,
        "PurchaseOfPPE": -13186000000.0,
        "RepaymentOfDebt": -2423000000.0,
        "RepurchaseOfCapitalStock": -15684000000.0,
        "SaleOfInvestment": 33884000000.0,
        "StockBasedCompensation": 5865000000.0
    },
    {
        "asOfDate": "2024-09-30 00:00:00",
        "periodType": "3M",
        "currencyCode": "USD",
        "AmortizationCashFlow": NaN,
        "AmortizationOfIntangibles": NaN,
        "BeginningCashPosition": 27225000000.0,
        "CapitalExpenditure": -13061000000.0,
        "CashDividendsPaid": -2455000000.0,
        "CashFlowFromContinuingFinancingActivities": -20094000000.0,
        "CashFlowFromContinuingInvestingActivities": -18011000000.0,
        "CashFlowFromContinuingOperatingActivities": 30698000000.0,
        "ChangeInAccountPayable": 521000000.0,
        "ChangeInAccruedExpense": -809000000.0,
        "ChangeInCashSupplementalAsReported": -7266000000.0,
        "ChangeInOtherCurrentAssets": -802000000.0,
        "ChangeInOtherWorkingCapital": 1529000000.0,
        "ChangeInPayable": -2276000000.0,
        "ChangeInPayablesAndAccruedExpense": -3085000000.0,
        "ChangeInReceivables": -1431000000.0,
        "ChangeInWorkingCapital": -3789000000.0,
        "ChangesInAccountReceivables": -1431000000.0,
        "ChangesInCash": -7407000000.0,
        "CommonStockDividendPaid": -2455000000.0,
        "CommonStockPayments": -15291000000.0,
        "DeferredIncomeTax": -1071000000.0,
        "DeferredTax": -1071000000.0,
        "Depreciation": 3985000000.0,
        "DepreciationAmortizationDepletion": 3985000000.0,
        "DepreciationAndAmortization": 3985000000.0,
        "EffectOfExchangeRateChanges": 141000000.0,
        "EndCashPosition": 19959000000.0,
        "FinancingCashFlow": -20094000000.0,
        "FreeCashFlow": 17637000000.0,
        "GainLossOnInvestmentSecurities": -1981000000.0,
        "InvestingCashFlow": -18011000000.0,
        "IssuanceOfDebt": 3819000000.0,
        "LongTermDebtIssuance": 3819000000.0,
        "LongTermDebtPayments": -3449000000.0,
        "NetBusinessPurchaseAndSale": -2753000000.0,
        "NetCommonStockIssuance": -15291000000.0,
        "NetIncome": 26301000000.0,
        "NetIncomeFromContinuingOperations": 26301000000.0,
        "NetInvestmentPurchaseAndSale": 271000000.0,
        "NetIssuancePaymentsOfDebt": 370000000.0,
        "NetLongTermDebtIssuance": 370000000.0,
        "NetOtherFinancingCharges": 285000000.0,
        "NetOtherInvestingChanges": -2468000000.0,
        "NetPPEPurchaseAndSale": -13061000000.0,
        "OperatingCashFlow": 30698000000.0,
        "OperatingGainsLosses": -1981000000.0,
        "OtherNonCashItems": 1407000000.0,
        "ProceedsFromStockOptionExercised": -3003000000.0,
        "PurchaseOfBusiness": -2753000000.0,
        "PurchaseOfInvestment": -23058000000.0,
        "PurchaseOfPPE": -13061000000.0,
        "RepaymentOfDebt": -3449000000.0,
        "RepurchaseOfCapitalStock": -15291000000.0,
        "SaleOfInvestment": 23329000000.0,
        "StockBasedCompensation": 5846000000.0
    },
    {
        "asOfDate": "2024-12-31 00:00:00",
        "periodType": "3M",
        "currencyCode": "USD",
        "AmortizationCashFlow": NaN,
        "AmortizationOfIntangibles": NaN,
        "BeginningCashPosition": 19959000000.0,
        "CapitalExpenditure": -14276000000.0,
        "CashDividendsPaid": -2442000000.0,
        "CashFlowFromContinuingFinancingActivities": -19036000000.0,
        "CashFlowFromContinuingInvestingActivities": -16180000000.0,
        "CashFlowFromContinuingOperatingActivities": 39113000000.0,
        "ChangeInAccountPayable": 401000000.0,
        "ChangeInAccruedExpense": 5786000000.0,
        "ChangeInCashSupplementalAsReported": 3507000000.0,
        "ChangeInOtherCurrentAssets": 937000000.0,
        "ChangeInOtherWorkingCapital": -2235000000.0,
        "ChangeInPayable": 3198000000.0,
        "ChangeInPayablesAndAccruedExpense": 8984000000.0,
        "ChangeInReceivables": -4570000000.0,
        "ChangeInWorkingCapital": 3116000000.0,
        "ChangesInAccountReceivables": -4570000000.0,
        "ChangesInCash": 3897000000.0,
        "CommonStockDividendPaid": -2442000000.0,
        "CommonStockPayments": -15551000000.0,
        "DeferredIncomeTax": -1448000000.0,
        "DeferredTax": -1448000000.0,
        "Depreciation": 4205000000.0,
        "DepreciationAmortizationDepletion": 4205000000.0,
        "DepreciationAndAmortization": 4205000000.0,
        "EffectOfExchangeRateChanges": -390000000.0,
        "EndCashPosition": 23466000000.0,
        "FinancingCashFlow": -19036000000.0,
        "FreeCashFlow": 24837000000.0,
        "GainLossOnInvestmentSecurities": 67000000.0,
        "InvestingCashFlow": -16180000000.0,
        "IssuanceOfDebt": 4895000000.0,
        "LongTermDebtIssuance": 4895000000.0,
        "LongTermDebtPayments": -3750000000.0,
        "NetBusinessPurchaseAndSale": -91000000.0,
        "NetCommonStockIssuance": -15551000000.0,
        "NetIncome": 26536000000.0,
        "NetIncomeFromContinuingOperations": 26536000000.0,
        "NetInvestmentPurchaseAndSale": -1646000000.0,
        "NetIssuancePaymentsOfDebt": 1145000000.0,
        "NetLongTermDebtIssuance": 1145000000.0,
        "NetOtherFinancingCharges": 861000000.0,
        "NetOtherInvestingChanges": -167000000.0,
        "NetPPEPurchaseAndSale": -14276000000.0,
        "OperatingCashFlow": 39113000000.0,
        "OperatingGainsLosses": 67000000.0,
        "OtherNonCashItems": 827000000.0,
        "ProceedsFromStockOptionExercised": -3049000000.0,
        "PurchaseOfBusiness": -91000000.0,
        "PurchaseOfInvestment": -23445000000.0,
        "PurchaseOfPPE": -14276000000.0,
        "RepaymentOfDebt": -3750000000.0,
        "RepurchaseOfCapitalStock": -15551000000.0,
        "SaleOfInvestment": 21799000000.0,
        "StockBasedCompensation": 5810000000.0
    },
    {
        "asOfDate": "2025-03-31 00:00:00",
        "periodType": "3M",
        "currencyCode": "USD",
        "AmortizationCashFlow": NaN,
        "AmortizationOfIntangibles": NaN,
        "BeginningCashPosition": 23466000000.0,
        "CapitalExpenditure": -17197000000.0,
        "CashDividendsPaid": -2434000000.0,
        "CashFlowFromContinuingFinancingActivities": -20201000000.0,
        "CashFlowFromContinuingInvestingActivities": -16194000000.0,
        "CashFlowFromContinuingOperatingActivities": 36150000000.0,
        "ChangeInAccountPayable": -880000000.0,
        "ChangeInAccruedExpense": -4929000000.0,
        "ChangeInCashSupplementalAsReported": -202000000.0,
        "ChangeInOtherCurrentAssets": -1288000000.0,
        "ChangeInOtherWorkingCapital": 7697000000.0,
        "ChangeInPayable": -880000000.0,
        "ChangeInPayablesAndAccruedExpense": -5809000000.0,
        "ChangeInReceivables": 1638000000.0,
        "ChangeInWorkingCapital": 2238000000.0,
        "ChangesInAccountReceivables": 1638000000.0,
        "ChangesInCash": -245000000.0,
        "CommonStockDividendPaid": -2434000000.0,
        "CommonStockPayments": -15068000000.0,
        "DeferredIncomeTax": -1152000000.0,
        "DeferredTax": -1152000000.0,
        "Depreciation": 4487000000.0,
        "DepreciationAmortizationDepletion": 4487000000.0,
        "DepreciationAndAmortization": 4487000000.0,
        "EffectOfExchangeRateChanges": 43000000.0,
        "EndCashPosition": 23264000000.0,
        "FinancingCashFlow": -20201000000.0,
        "FreeCashFlow": 18953000000.0,
        "GainLossOnInvestmentSecurities": -9960000000.0,
        "InvestingCashFlow": -16194000000.0,
        "IssuanceOfDebt": 4532000000.0,
        "LongTermDebtIssuance": 4532000000.0,
        "LongTermDebtPayments": -4521000000.0,
        "NetBusinessPurchaseAndSale": -340000000.0,
        "NetCommonStockIssuance": -15068000000.0,
        "NetIncome": 34540000000.0,
        "NetIncomeFromContinuingOperations": 34540000000.0,
        "NetInvestmentPurchaseAndSale": 1193000000.0,
        "NetIssuancePaymentsOfDebt": 11000000.0,
        "NetLongTermDebtIssuance": 11000000.0,
        "NetOtherFinancingCharges": 400000000.0,
        "NetOtherInvestingChanges": 150000000.0,
        "NetPPEPurchaseAndSale": -17197000000.0,
        "OperatingCashFlow": 36150000000.0,
        "OperatingGainsLosses": -9960000000.0,
        "OtherNonCashItems": 481000000.0,
        "ProceedsFromStockOptionExercised": -3110000000.0,
        "PurchaseOfBusiness": -340000000.0,
        "PurchaseOfInvestment": -19411000000.0,
        "PurchaseOfPPE": -17197000000.0,
        "RepaymentOfDebt": -4521000000.0,
        "RepurchaseOfCapitalStock": -15068000000.0,
        "SaleOfInvestment": 20604000000.0,
        "StockBasedCompensation": 5516000000.0
    },
    {
        "asOfDate": "2025-03-31 00:00:00",
        "periodType": "TTM",
        "currencyCode": "USD",
        "AmortizationCashFlow": NaN,
        "AmortizationOfIntangibles": NaN,
        "BeginningCashPosition": 24493000000.0,
        "CapitalExpenditure": -57720000000.0,
        "CashDividendsPaid": -9797000000.0,
        "CashFlowFromContinuingFinancingActivities": -80220000000.0,
        "CashFlowFromContinuingInvestingActivities": -53166000000.0,
        "CashFlowFromContinuingOperatingActivities": 132601000000.0,
        "ChangeInAccountPayable": 1603000000.0,
        "ChangeInAccruedExpense": 345000000.0,
        "ChangeInCashSupplementalAsReported": -1229000000.0,
        "ChangeInOtherCurrentAssets": -1685000000.0,
        "ChangeInOtherWorkingCapital": 3452000000.0,
        "ChangeInPayable": 1603000000.0,
        "ChangeInPayablesAndAccruedExpense": 1948000000.0,
        "ChangeInReceivables": -7420000000.0,
        "ChangeInWorkingCapital": -3705000000.0,
        "ChangesInAccountReceivables": -7420000000.0,
        "ChangesInCash": -785000000.0,
        "CommonStockDividendPaid": -9797000000.0,
        "CommonStockPayments": -61594000000.0,
        "DeferredIncomeTax": -6828000000.0,
        "DeferredTax": -6828000000.0,
        "Depreciation": 16385000000.0,
        "DepreciationAmortizationDepletion": 16385000000.0,
        "DepreciationAndAmortization": 16385000000.0,
        "EffectOfExchangeRateChanges": -444000000.0,
        "EndCashPosition": 23708000000.0,
        "FinancingCashFlow": -80220000000.0,
        "FreeCashFlow": 74881000000.0,
        "GainLossOnInvestmentSecurities": -10850000000.0,
        "InvestingCashFlow": -53166000000.0,
        "IssuanceOfDebt": 16139000000.0,
        "LongTermDebtIssuance": 16139000000.0,
        "LongTermDebtPayments": -14143000000.0,
        "NetBusinessPurchaseAndSale": -3210000000.0,
        "NetCommonStockIssuance": -61594000000.0,
        "NetIncome": 110996000000.0,
        "NetIncomeFromContinuingOperations": 110996000000.0,
        "NetInvestmentPurchaseAndSale": 10382000000.0,
        "NetIssuancePaymentsOfDebt": 1996000000.0,
        "NetLongTermDebtIssuance": 1996000000.0,
        "NetOtherFinancingCharges": 1546000000.0,
        "NetOtherInvestingChanges": -2618000000.0,
        "NetPPEPurchaseAndSale": -57720000000.0,
        "OperatingCashFlow": 132601000000.0,
        "OperatingGainsLosses": -10850000000.0,
        "OtherNonCashItems": 3566000000.0,
        "ProceedsFromStockOptionExercised": -12371000000.0,
        "PurchaseOfBusiness": -3210000000.0,
        "PurchaseOfInvestment": -89234000000.0,
        "PurchaseOfPPE": -57720000000.0,
        "RepaymentOfDebt": -14143000000.0,
        "RepurchaseOfCapitalStock": -61594000000.0,
        "SaleOfInvestment": 99616000000.0,
        "StockBasedCompensation": 23037000000.0
    }
]