{
    "googl": {
        "maxAge": 1,
        "preMarketSource": "FREE_REALTIME",
        "postMarketChangePercent": -0.0032258115,
        "postMarketChange": -0.55400085,
        "postMarketTime": "2025-05-31 08:59:42",
        "postMarketPrice": 171.186,
        "postMarketSource": "DELAYED",
        "regularMarketChangePercent": -0.00069821405,
        "regularMarketChange": -0.119995,
        "regularMarketTime": "2025-05-31 05:00:02",
        "priceHint": 2,
        "regularMarketPrice": 171.74,
        "regularMarketDayHigh": 172.205,
        "regularMarketDayLow": 167.45,
        "regularMarketVolume": 50692552,
        "regularMarketPreviousClose": 171.86,
        "regularMarketSource": "FREE_REALTIME",
        "regularMarketOpen": 171.36,
        "exchange": "NMS",
        "exchangeName": "NasdaqGS",
        "exchangeDataDelayedBy": 0,
        "marketState": "CLOSED",
        "quoteType": "EQUITY",
        "symbol": "GOOGL",
        "underlyingSymbol": null,
        "shortName": "Alphabet Inc.",
        "longName": "Alphabet Inc.",
        "currency": "USD",
        "quoteSourceName": "Delayed Quote",
        "currencySymbol": "$",
        "fromCurrency": null,
        "toCurrency": null,
        "lastMarket": null,
        "marketCap": 2090075947008
    }
}